examples/__init__.py
examples/train_example.py
mlchemy/__init__.py
mlchemy/model.py
mlchemy/preprocessing.py
mlchemy/utils.py
mlchemy/validation.py
mlchemy-0.1.0.dist-info/licenses/LICENSE
mlchemy-0.1.0.dist-info/METADATA
mlchemy-0.1.0.dist-info/WHEEL
mlchemy-0.1.0.dist-info/entry_points.txt
mlchemy-0.1.0.dist-info/top_level.txt
mlchemy-0.1.0.dist-info/RECORD
